[
    {
        "SubscriptionId": "38c26c07-ccce-4839-b504-cddac8e5b09d",
        "TotalCost": 3987.353026832953,
        "AverageDailyCost": 132.91176756109843,
        "MaximumDailyCost": 195.934436839538,
        "MinimumDailyCost": 116.817712322877
    },
    {
        "SubscriptionId": "c916841c-459e-4bbd-aff7-c235ae45f0dd",
        "TotalCost": 234.26633314934458,
        "AverageDailyCost": 7.808877771644819,
        "MaximumDailyCost": 25.1058726665755,
        "MinimumDailyCost": 4.04320111565548
    },
    {
        "SubscriptionId": "9d923c47-1aa2-4fc9-856f-16ca53e97b76",
        "TotalCost": 806.3064494668582,
        "AverageDailyCost": 26.876881648895274,
        "MaximumDailyCost": 50.4891908067946,
        "MinimumDailyCost": 0.003712
    }
]